{"ts": "2026-03-10T08:57:32.852Z", "level": "info", "service": "redis_capacity_loadtest", "service_instance": "yksl:32860", "event": "loadtest.redis_capacity.summary", "message": "redis capacity load test completed", "thread": "MainThread", "request_id": "", "span_id": "", "uid": "", "session_id": "", "module": "redis_capacity_load", "peer_service": "", "error_code": "", "error_type": "", "duration_ms": 0, "attrs": {"scenario": "redis_capacity", "total": 80, "concurrency": 8, "success": 80, "failed": 0, "rps": 260.896, "p95": 163.014, "p99": 174.666, "top_errors": {}, "report": "D:\\MemoChat-Qml-Drogon\\local-loadtest\\..\\Memo_ops\\runtime\\loadtest\\reports\\suite_20260310_015359\\12_redis_capacity.json"}}
{"ts": "2026-03-10T09:18:29.159Z", "level": "info", "service": "redis_capacity_loadtest", "service_instance": "yksl:27152", "event": "loadtest.redis_capacity.summary", "message": "redis capacity load test completed", "thread": "MainThread", "request_id": "", "span_id": "", "uid": "", "session_id": "", "module": "redis_capacity_load", "peer_service": "", "error_code": "", "error_type": "", "duration_ms": 0, "attrs": {"scenario": "redis_capacity", "total": 80, "concurrency": 8, "success": 80, "failed": 0, "rps": 249.936, "p95": 173.003, "p99": 179.886, "top_errors": {}, "report": "D:\\MemoChat-Qml-Drogon\\local-loadtest\\..\\Memo_ops\\runtime\\loadtest\\reports\\suite_20260310_021123\\12_redis_capacity.json"}}
